randar303/__init__.py
randar303/main.py
randar303-0.1.1.dist-info/METADATA
randar303-0.1.1.dist-info/WHEEL
randar303-0.1.1.dist-info/entry_points.txt
randar303-0.1.1.dist-info/top_level.txt
randar303-0.1.1.dist-info/RECORD
